foundation_kaia/__init__.py
foundation_kaia/fork/__init__.py
foundation_kaia/fork/fork.py
foundation_kaia/fork/fork_app.py
foundation_kaia/fork/fork_worker.py
foundation_kaia/marshalling/__init__.py
foundation_kaia/marshalling/api.py
foundation_kaia/marshalling/api_binding.py
foundation_kaia/marshalling/api_utils.py
foundation_kaia/marshalling/endpoint.py
foundation_kaia/marshalling/format.py
foundation_kaia/marshalling/marshalling_metadata.py
foundation_kaia/marshalling/server.py
foundation_kaia/marshalling/server_binding.py
foundation_kaia/marshalling/signature_processor.py
foundation_kaia/marshalling/test_api.py
foundation_kaia/misc/__init__.py
foundation_kaia/misc/loc.py
foundation_kaia/misc/pickle_test.py
foundation_kaia/misc/scheduled_time.py
foundation_kaia/prompters/__init__.py
foundation_kaia/prompters/abstract_prompter.py
foundation_kaia/prompters/address.py
foundation_kaia/prompters/address_builder.py
foundation_kaia/prompters/jinja_prompter.py
foundation_kaia/prompters/prompter.py
foundation_kaia/prompters/referrer.py
foundation_kaia/prompters/template_parts.py
foundation_kaia/web_utils/__init__.py
foundation_kaia/web_utils/common.py
foundation_kaia/web_utils/file_cache/__init__.py
foundation_kaia/web_utils/file_cache/api.py
foundation_kaia/web_utils/file_cache/component.py
kaia_foundation-4.0.9.dist-info/METADATA
kaia_foundation-4.0.9.dist-info/WHEEL
kaia_foundation-4.0.9.dist-info/top_level.txt
kaia_foundation-4.0.9.dist-info/RECORD
