Metadata-Version: 2.4
Name: kaia-foundation
Version: 4.0.9
Summary: Utilities used in Kaia project
Author-email: Yuri Okulovsky <yuri.okulovsky@gmail.com>
License-Expression: LGPL-3.0-or-later
Project-URL: repository, https://github.com/okulovsky/kaia/tree/main/foundation_kaia
Classifier: Programming Language :: Python :: 3.10
Classifier: Programming Language :: Python :: 3.11
Classifier: Programming Language :: Python :: 3.12
Classifier: Programming Language :: Python :: 3.13
Classifier: Intended Audience :: Developers
Classifier: Intended Audience :: Science/Research
Classifier: Intended Audience :: Information Technology
Classifier: Topic :: Scientific/Engineering :: Artificial Intelligence
Classifier: Development Status :: 4 - Beta
Requires-Python: <4.0,>=3.10
Requires-Dist: yo_fluq
Requires-Dist: requests
Requires-Dist: jsonpickle
Requires-Dist: Jinja2
Requires-Dist: flask
Requires-Dist: python-dotenv
